extendableenum/__init__.py
extendableenum/extendableenum.py
extendable_enum-1.0.1.dist-info/LICENSE
extendable_enum-1.0.1.dist-info/METADATA
extendable_enum-1.0.1.dist-info/WHEEL
extendable_enum-1.0.1.dist-info/top_level.txt
extendable_enum-1.0.1.dist-info/RECORD
