Metadata-Version: 2.1
Name: extendable-enum
Version: 1.0.1
Summary: A utility package for extending, subclassing and reusing Enum classes.
Home-page: https://github.com/gweesip/extendable-enum
Author: AJ Marasco
Author-email: aj.marasco88@gmail.com
Project-URL: Bug Tracker, https://github.com/gweesip/extendable-enum/issues
Project-URL: Documentation, https://extendable-enum.readthedocs.io/en/latest/
Classifier: Programming Language :: Python :: 3
Classifier: License :: OSI Approved :: GNU General Public License v3 (GPLv3)
Classifier: Operating System :: OS Independent
Requires-Python: >=3.6
License-File: LICENSE
